llama_index/retrievers/tldw/__init__.py
llama_index/retrievers/tldw/base.py
llama_index_retrievers_tldw-0.1.1.dist-info/METADATA
llama_index_retrievers_tldw-0.1.1.dist-info/WHEEL
llama_index_retrievers_tldw-0.1.1.dist-info/RECORD
