Metadata-Version: 2.4
Name: llama-index-retrievers-tldw
Version: 0.1.1
Summary: llama-index retrievers tl;dw AI integration
Author-email: Shihang W <sw@trytldw.ai>
License-Expression: MIT
Requires-Python: <4.0,>=3.9
Requires-Dist: llama-index-core<0.15,>=0.13.0
